{
  "session_id": "20260327_005229",
  "saved_prefix": "20260327_005229",
  "saved_at": "2026-03-27 00:59:02 CST",
  "frame_id": "map",
  "map_yaml": "20260327_005229.yaml",
  "exploration_status": "running",
  "filtered_frontier_count": 4,
  "goals": [
    {
      "id": 0,
      "robot_name": "",
      "x": 2.2633925676345825,
      "y": 1.0291325449943542,
      "status": "reached",
      "nav_status": 4,
      "assigned_at": "2026-03-27 00:53:22 CST",
      "reached_at": "2026-03-27 00:53:33 CST",
      "failed_at": "",
      "canceled_at": ""
    },
    {
      "id": 1,
      "robot_name": "",
      "x": 0.17178055030547057,
      "y": 0.009519596519112383,
      "status": "reached",
      "nav_status": 4,
      "assigned_at": "2026-03-27 00:53:35 CST",
      "reached_at": "2026-03-27 00:53:55 CST",
      "failed_at": "",
      "canceled_at": ""
    },
    {
      "id": 2,
      "robot_name": "",
      "x": 5.16241979598999,
      "y": 0.40767785906791687,
      "status": "reached",
      "nav_status": 4,
      "assigned_at": "2026-03-27 00:53:56 CST",
      "reached_at": "2026-03-27 00:54:14 CST",
      "failed_at": "",
      "canceled_at": ""
    },
    {
      "id": 3,
      "robot_name": "",
      "x": 1.6398276450711364,
      "y": -3.5461493567734883,
      "status": "reached",
      "nav_status": 4,
      "assigned_at": "2026-03-27 00:54:14 CST",
      "reached_at": "2026-03-27 00:54:56 CST",
      "failed_at": "",
      "canceled_at": ""
    },
    {
      "id": 4,
      "robot_name": "",
      "x": 7.5805979172388716,
      "y": 0.9386008729537328,
      "status": "reached",
      "nav_status": 4,
      "assigned_at": "2026-03-27 00:54:56 CST",
      "reached_at": "2026-03-27 00:55:45 CST",
      "failed_at": "",
      "canceled_at": ""
    },
    {
      "id": 5,
      "robot_name": "",
      "x": 10.235808372497559,
      "y": 1.3610522747039795,
      "status": "reached",
      "nav_status": 4,
      "assigned_at": "2026-03-27 00:55:45 CST",
      "reached_at": "2026-03-27 00:55:58 CST",
      "failed_at": "",
      "canceled_at": ""
    },
    {
      "id": 6,
      "robot_name": "",
      "x": 11.259470806549823,
      "y": 1.6840106769469985,
      "status": "reached",
      "nav_status": 4,
      "assigned_at": "2026-03-27 00:55:58 CST",
      "reached_at": "2026-03-27 00:56:18 CST",
      "failed_at": "",
      "canceled_at": ""
    },
    {
      "id": 7,
      "robot_name": "",
      "x": 14.70803096764126,
      "y": 1.8165803505102804,
      "status": "reached",
      "nav_status": 4,
      "assigned_at": "2026-03-27 00:56:18 CST",
      "reached_at": "2026-03-27 00:56:37 CST",
      "failed_at": "",
      "canceled_at": ""
    },
    {
      "id": 8,
      "robot_name": "",
      "x": -0.1045296176453121,
      "y": 1.287305964001765,
      "status": "failed",
      "nav_status": 6,
      "assigned_at": "2026-03-27 00:56:37 CST",
      "reached_at": "",
      "failed_at": "2026-03-27 00:57:01 CST",
      "canceled_at": ""
    },
    {
      "id": 9,
      "robot_name": "",
      "x": 15.543497119249432,
      "y": 2.2638682483230284,
      "status": "reached",
      "nav_status": 4,
      "assigned_at": "2026-03-27 00:57:01 CST",
      "reached_at": "2026-03-27 00:58:12 CST",
      "failed_at": "",
      "canceled_at": ""
    },
    {
      "id": 10,
      "robot_name": "",
      "x": -0.1045296176453121,
      "y": 1.287305964001765,
      "status": "failed",
      "nav_status": 6,
      "assigned_at": "2026-03-27 00:58:12 CST",
      "reached_at": "",
      "failed_at": "2026-03-27 00:58:32 CST",
      "canceled_at": ""
    },
    {
      "id": 11,
      "robot_name": "",
      "x": 1.1968101263046265,
      "y": -3.280473470687866,
      "status": "assigned",
      "nav_status": 1,
      "assigned_at": "2026-03-27 00:58:33 CST",
      "reached_at": "",
      "failed_at": "",
      "canceled_at": ""
    }
  ],
  "trajectory": [
    {
      "x": 0.0,
      "y": 0.0,
      "t": "2026-03-27 00:52:30 CST"
    },
    {
      "x": 0.05920162537592811,
      "y": 0.003049015447182419,
      "t": "2026-03-27 00:53:22 CST"
    },
    {
      "x": 0.14425627653153422,
      "y": 0.018621046875738477,
      "t": "2026-03-27 00:53:23 CST"
    },
    {
      "x": 0.19272398075568775,
      "y": 0.03396988468564904,
      "t": "2026-03-27 00:53:23 CST"
    },
    {
      "x": 0.24390778506668015,
      "y": 0.052523444628384736,
      "t": "2026-03-27 00:53:23 CST"
    },
    {
      "x": 0.2900366459844365,
      "y": 0.07431221367848048,
      "t": "2026-03-27 00:53:23 CST"
    },
    {
      "x": 0.3793706091755107,
      "y": 0.12049261104457405,
      "t": "2026-03-27 00:53:24 CST"
    },
    {
      "x": 0.42501735349826847,
      "y": 0.1459597340060275,
      "t": "2026-03-27 00:53:24 CST"
    },
    {
      "x": 0.46954586007500937,
      "y": 0.1715901149081238,
      "t": "2026-03-27 00:53:24 CST"
    },
    {
      "x": 0.521289505699137,
      "y": 0.24626414605079353,
      "t": "2026-03-27 00:53:25 CST"
    },
    {
      "x": 0.5703969308854355,
      "y": 0.26390298128220624,
      "t": "2026-03-27 00:53:25 CST"
    },
    {
      "x": 0.6203696834288159,
      "y": 0.27751473295961515,
      "t": "2026-03-27 00:53:25 CST"
    },
    {
      "x": 0.717847427453613,
      "y": 0.296083093792273,
      "t": "2026-03-27 00:53:25 CST"
    },
    {
      "x": 0.7697609575166263,
      "y": 0.30426001426863986,
      "t": "2026-03-27 00:53:26 CST"
    },
    {
      "x": 0.8202513527209967,
      "y": 0.31247754271392414,
      "t": "2026-03-27 00:53:26 CST"
    },
    {
      "x": 0.8729218220587885,
      "y": 0.32114878635717364,
      "t": "2026-03-27 00:53:26 CST"
    },
    {
      "x": 0.9253378504261345,
      "y": 0.3323611800316252,
      "t": "2026-03-27 00:53:26 CST"
    },
    {
      "x": 0.9771317923557128,
      "y": 0.3449524066132181,
      "t": "2026-03-27 00:53:26 CST"
    },
    {
      "x": 1.0276501891700307,
      "y": 0.35900947842484426,
      "t": "2026-03-27 00:53:27 CST"
    },
    {
      "x": 1.077888618762325,
      "y": 0.3747364272437529,
      "t": "2026-03-27 00:53:27 CST"
    },
    {
      "x": 1.1260463311652067,
      "y": 0.3916310320517582,
      "t": "2026-03-27 00:53:27 CST"
    },
    {
      "x": 1.1729686363033291,
      "y": 0.4101826131625558,
      "t": "2026-03-27 00:53:27 CST"
    },
    {
      "x": 1.2200097339499785,
      "y": 0.42859936455275943,
      "t": "2026-03-27 00:53:27 CST"
    },
    {
      "x": 1.3092438247102602,
      "y": 0.46546660281953217,
      "t": "2026-03-27 00:53:28 CST"
    },
    {
      "x": 1.3566642421536308,
      "y": 0.4847248107042081,
      "t": "2026-03-27 00:53:28 CST"
    },
    {
      "x": 1.4533385612714051,
      "y": 0.5370197159992806,
      "t": "2026-03-27 00:53:28 CST"
    },
    {
      "x": 1.5089646040393279,
      "y": 0.5634195058809328,
      "t": "2026-03-27 00:53:28 CST"
    },
    {
      "x": 1.5552341511835375,
      "y": 0.5824470969782974,
      "t": "2026-03-27 00:53:29 CST"
    },
    {
      "x": 1.6014816410816033,
      "y": 0.6014884642152384,
      "t": "2026-03-27 00:53:29 CST"
    },
    {
      "x": 1.6931583367145921,
      "y": 0.6368937584415315,
      "t": "2026-03-27 00:53:29 CST"
    },
    {
      "x": 1.7862612345068276,
      "y": 0.6739984493843009,
      "t": "2026-03-27 00:53:30 CST"
    },
    {
      "x": 1.8355104503270414,
      "y": 0.6935169257871726,
      "t": "2026-03-27 00:53:30 CST"
    },
    {
      "x": 1.8827740596064704,
      "y": 0.7125172706944879,
      "t": "2026-03-27 00:53:30 CST"
    },
    {
      "x": 1.9310901147931,
      "y": 0.7315052193606476,
      "t": "2026-03-27 00:53:30 CST"
    },
    {
      "x": 1.9781870115095654,
      "y": 0.7531764204647616,
      "t": "2026-03-27 00:53:30 CST"
    },
    {
      "x": 2.0259154372345827,
      "y": 0.7759670353418345,
      "t": "2026-03-27 00:53:31 CST"
    },
    {
      "x": 2.1062250671418865,
      "y": 0.8216500723591722,
      "t": "2026-03-27 00:53:31 CST"
    },
    {
      "x": 2.148661821198256,
      "y": 0.8515451140849576,
      "t": "2026-03-27 00:53:31 CST"
    },
    {
      "x": 2.171326682684856,
      "y": 0.8649140524873178,
      "t": "2026-03-27 00:53:33 CST"
    },
    {
      "x": 2.1757720518721078,
      "y": 0.8251539477475411,
      "t": "2026-03-27 00:53:36 CST"
    },
    {
      "x": 2.173234552216451,
      "y": 0.7896788855550239,
      "t": "2026-03-27 00:53:38 CST"
    },
    {
      "x": 2.1463201268528476,
      "y": 0.7214354593086206,
      "t": "2026-03-27 00:53:38 CST"
    },
    {
      "x": 2.075605008915823,
      "y": 0.6581635189870426,
      "t": "2026-03-27 00:53:39 CST"
    },
    {
      "x": 1.9853467061671923,
      "y": 0.6265157874104239,
      "t": "2026-03-27 00:53:39 CST"
    },
    {
      "x": 1.89456320202566,
      "y": 0.6192658476574815,
      "t": "2026-03-27 00:53:40 CST"
    },
    {
      "x": 1.7971354924285672,
      "y": 0.6115633732936018,
      "t": "2026-03-27 00:53:40 CST"
    },
    {
      "x": 1.7459199187114773,
      "y": 0.6035127606528198,
      "t": "2026-03-27 00:53:40 CST"
    },
    {
      "x": 1.6971577122904906,
      "y": 0.5905524106935224,
      "t": "2026-03-27 00:53:40 CST"
    },
    {
      "x": 1.6386322676753726,
      "y": 0.5635168555376172,
      "t": "2026-03-27 00:53:41 CST"
    },
    {
      "x": 1.5454849517571643,
      "y": 0.527722419082346,
      "t": "2026-03-27 00:53:41 CST"
    },
    {
      "x": 1.4981298635436506,
      "y": 0.5097134091965227,
      "t": "2026-03-27 00:53:42 CST"
    },
    {
      "x": 1.4493714427492579,
      "y": 0.4909428994950964,
      "t": "2026-03-27 00:53:42 CST"
    },
    {
      "x": 1.401679280192559,
      "y": 0.47176527834772763,
      "t": "2026-03-27 00:53:42 CST"
    },
    {
      "x": 1.3537676736692759,
      "y": 0.45269566164784736,
      "t": "2026-03-27 00:53:42 CST"
    },
    {
      "x": 1.3063223414684666,
      "y": 0.43497128504366306,
      "t": "2026-03-27 00:53:42 CST"
    },
    {
      "x": 1.258056595056173,
      "y": 0.41662717182012093,
      "t": "2026-03-27 00:53:43 CST"
    },
    {
      "x": 1.2104165568232697,
      "y": 0.39970170400757454,
      "t": "2026-03-27 00:53:43 CST"
    },
    {
      "x": 1.1632999237617987,
      "y": 0.38289056386202164,
      "t": "2026-03-27 00:53:43 CST"
    },
    {
      "x": 1.115146961619177,
      "y": 0.36647755527956755,
      "t": "2026-03-27 00:53:43 CST"
    },
    {
      "x": 1.0658506936540182,
      "y": 0.34970375868764053,
      "t": "2026-03-27 00:53:43 CST"
    },
    {
      "x": 1.0165413896686417,
      "y": 0.33354775273632986,
      "t": "2026-03-27 00:53:44 CST"
    },
    {
      "x": 0.9665561237564227,
      "y": 0.31728965421411376,
      "t": "2026-03-27 00:53:44 CST"
    },
    {
      "x": 0.9173739074317476,
      "y": 0.30047551362835856,
      "t": "2026-03-27 00:53:44 CST"
    },
    {
      "x": 0.8634723745803019,
      "y": 0.2849675538970515,
      "t": "2026-03-27 00:53:44 CST"
    },
    {
      "x": 0.7850571207131736,
      "y": 0.28005714633272627,
      "t": "2026-03-27 00:53:44 CST"
    },
    {
      "x": 0.7327846283293064,
      "y": 0.262009466038783,
      "t": "2026-03-27 00:53:45 CST"
    },
    {
      "x": 0.6821276770517775,
      "y": 0.24160968833362464,
      "t": "2026-03-27 00:53:45 CST"
    },
    {
      "x": 0.6355959753547108,
      "y": 0.22077045077833224,
      "t": "2026-03-27 00:53:45 CST"
    },
    {
      "x": 0.5609115957426264,
      "y": 0.18366492606168572,
      "t": "2026-03-27 00:53:45 CST"
    },
    {
      "x": 0.5159180376535583,
      "y": 0.160484059849273,
      "t": "2026-03-27 00:53:46 CST"
    },
    {
      "x": 0.4886302066198344,
      "y": 0.14502517202135706,
      "t": "2026-03-27 00:53:46 CST"
    },
    {
      "x": 0.46695568310354996,
      "y": 0.13123690764357732,
      "t": "2026-03-27 00:53:48 CST"
    },
    {
      "x": 0.43981859655281835,
      "y": 0.1254227270350168,
      "t": "2026-03-27 00:53:51 CST"
    },
    {
      "x": 0.4720198056520403,
      "y": 0.12189891670795451,
      "t": "2026-03-27 00:53:56 CST"
    },
    {
      "x": 0.5551535013010759,
      "y": 0.1125056182060886,
      "t": "2026-03-27 00:53:57 CST"
    },
    {
      "x": 0.6072856857366423,
      "y": 0.10925883299702985,
      "t": "2026-03-27 00:53:57 CST"
    },
    {
      "x": 0.7034591066125906,
      "y": 0.11215540369322853,
      "t": "2026-03-27 00:53:57 CST"
    },
    {
      "x": 0.7535718624440559,
      "y": 0.11431994644363173,
      "t": "2026-03-27 00:53:57 CST"
    },
    {
      "x": 0.8125120613860981,
      "y": 0.11712477968200448,
      "t": "2026-03-27 00:53:58 CST"
    },
    {
      "x": 0.905129215157253,
      "y": 0.12393073707301606,
      "t": "2026-03-27 00:53:58 CST"
    },
    {
      "x": 0.956001747304888,
      "y": 0.12572456787310948,
      "t": "2026-03-27 00:53:58 CST"
    },
    {
      "x": 1.0066985697991244,
      "y": 0.12551631001607264,
      "t": "2026-03-27 00:53:58 CST"
    },
    {
      "x": 1.0284989711288173,
      "y": 0.05562774523114046,
      "t": "2026-03-27 00:53:59 CST"
    },
    {
      "x": 1.0805615425896462,
      "y": 0.05222806213445008,
      "t": "2026-03-27 00:53:59 CST"
    },
    {
      "x": 1.1313429973856055,
      "y": 0.04864689955044926,
      "t": "2026-03-27 00:53:59 CST"
    },
    {
      "x": 1.184915515376853,
      "y": 0.04633645828294522,
      "t": "2026-03-27 00:53:59 CST"
    },
    {
      "x": 1.2838989053116898,
      "y": 0.044852928520618826,
      "t": "2026-03-27 00:54:00 CST"
    },
    {
      "x": 1.3339323318592715,
      "y": 0.04540997154749912,
      "t": "2026-03-27 00:54:00 CST"
    },
    {
      "x": 1.4302556326234133,
      "y": 0.04987836729759865,
      "t": "2026-03-27 00:54:00 CST"
    },
    {
      "x": 1.5277166696584317,
      "y": 0.054296799457087055,
      "t": "2026-03-27 00:54:01 CST"
    },
    {
      "x": 1.6259928842224913,
      "y": 0.058963975096848475,
      "t": "2026-03-27 00:54:01 CST"
    },
    {
      "x": 1.724757009667381,
      "y": 0.06160468046939413,
      "t": "2026-03-27 00:54:02 CST"
    },
    {
      "x": 1.776630858983874,
      "y": 0.06283937594323623,
      "t": "2026-03-27 00:54:02 CST"
    },
    {
      "x": 1.8280715961861878,
      "y": 0.061929711820981906,
      "t": "2026-03-27 00:54:02 CST"
    },
    {
      "x": 1.87860917058925,
      "y": 0.06021649136051552,
      "t": "2026-03-27 00:54:02 CST"
    },
    {
      "x": 2.0186453288563047,
      "y": 0.11574437587602333,
      "t": "2026-03-27 00:54:03 CST"
    },
    {
      "x": 2.1174298404226635,
      "y": 0.11102414098496591,
      "t": "2026-03-27 00:54:03 CST"
    },
    {
      "x": 2.2166184749974374,
      "y": 0.10244968677590602,
      "t": "2026-03-27 00:54:03 CST"
    },
    {
      "x": 2.267837886060527,
      "y": 0.09739323309550073,
      "t": "2026-03-27 00:54:04 CST"
    },
    {
      "x": 2.3201300803158076,
      "y": 0.0929861659736376,
      "t": "2026-03-27 00:54:04 CST"
    },
    {
      "x": 2.3731326052615955,
      "y": 0.08859963593496316,
      "t": "2026-03-27 00:54:04 CST"
    },
    {
      "x": 2.426525114915506,
      "y": 0.08419584108703863,
      "t": "2026-03-27 00:54:04 CST"
    },
    {
      "x": 2.477693638993402,
      "y": 0.08150401081985255,
      "t": "2026-03-27 00:54:04 CST"
    },
    {
      "x": 2.5301046011028445,
      "y": 0.0810648354940972,
      "t": "2026-03-27 00:54:05 CST"
    },
    {
      "x": 2.5810001220784544,
      "y": 0.08128048821454174,
      "t": "2026-03-27 00:54:05 CST"
    },
    {
      "x": 2.631752843140531,
      "y": 0.08225523172405542,
      "t": "2026-03-27 00:54:05 CST"
    },
    {
      "x": 2.7256269155064787,
      "y": 0.0882896877177623,
      "t": "2026-03-27 00:54:05 CST"
    },
    {
      "x": 2.823742626409879,
      "y": 0.09666768730701422,
      "t": "2026-03-27 00:54:06 CST"
    },
    {
      "x": 2.875309310271836,
      "y": 0.10076561693491007,
      "t": "2026-03-27 00:54:06 CST"
    },
    {
      "x": 2.965738583435656,
      "y": 0.12221398278235557,
      "t": "2026-03-27 00:54:06 CST"
    },
    {
      "x": 3.017189762173454,
      "y": 0.12443119369276173,
      "t": "2026-03-27 00:54:06 CST"
    },
    {
      "x": 3.1186787684257644,
      "y": 0.1253029477589184,
      "t": "2026-03-27 00:54:07 CST"
    },
    {
      "x": 3.170312352672382,
      "y": 0.12502165457624964,
      "t": "2026-03-27 00:54:07 CST"
    },
    {
      "x": 3.220927458964176,
      "y": 0.12423564591431774,
      "t": "2026-03-27 00:54:07 CST"
    },
    {
      "x": 3.272385798722563,
      "y": 0.12284185948502033,
      "t": "2026-03-27 00:54:07 CST"
    },
    {
      "x": 3.3247428646841257,
      "y": 0.12203212153462739,
      "t": "2026-03-27 00:54:08 CST"
    },
    {
      "x": 3.3765108480403,
      "y": 0.12189377641130583,
      "t": "2026-03-27 00:54:08 CST"
    },
    {
      "x": 3.476582362298793,
      "y": 0.12504060935583888,
      "t": "2026-03-27 00:54:08 CST"
    },
    {
      "x": 3.526940449615188,
      "y": 0.12704065229492553,
      "t": "2026-03-27 00:54:08 CST"
    },
    {
      "x": 3.6231013844850675,
      "y": 0.1317647434732936,
      "t": "2026-03-27 00:54:09 CST"
    },
    {
      "x": 3.723218886707436,
      "y": 0.13685366394533813,
      "t": "2026-03-27 00:54:09 CST"
    },
    {
      "x": 3.819193161233079,
      "y": 0.14079252944190232,
      "t": "2026-03-27 00:54:10 CST"
    },
    {
      "x": 3.908437337405484,
      "y": 0.1724929826566336,
      "t": "2026-03-27 00:54:10 CST"
    },
    {
      "x": 4.006686089914498,
      "y": 0.1758997485947313,
      "t": "2026-03-27 00:54:10 CST"
    },
    {
      "x": 4.104509326338563,
      "y": 0.1807165629719647,
      "t": "2026-03-27 00:54:11 CST"
    },
    {
      "x": 4.154501104722563,
      "y": 0.18169407556714534,
      "t": "2026-03-27 00:54:11 CST"
    },
    {
      "x": 4.252214095448587,
      "y": 0.18625151836315046,
      "t": "2026-03-27 00:54:11 CST"
    },
    {
      "x": 4.303817118210554,
      "y": 0.19045906719002892,
      "t": "2026-03-27 00:54:11 CST"
    },
    {
      "x": 4.355041354137337,
      "y": 0.19417632920180483,
      "t": "2026-03-27 00:54:12 CST"
    },
    {
      "x": 4.407007872578965,
      "y": 0.19914490935428952,
      "t": "2026-03-27 00:54:12 CST"
    },
    {
      "x": 4.457341727518503,
      "y": 0.20563948165005588,
      "t": "2026-03-27 00:54:12 CST"
    },
    {
      "x": 4.5085147505970875,
      "y": 0.21394409241367326,
      "t": "2026-03-27 00:54:12 CST"
    },
    {
      "x": 4.559468843961086,
      "y": 0.22128540314352674,
      "t": "2026-03-27 00:54:12 CST"
    },
    {
      "x": 4.657554382053929,
      "y": 0.23790908212456913,
      "t": "2026-03-27 00:54:13 CST"
    },
    {
      "x": 4.708303489361353,
      "y": 0.2479675014962861,
      "t": "2026-03-27 00:54:13 CST"
    },
    {
      "x": 4.758344247733669,
      "y": 0.25882171752329075,
      "t": "2026-03-27 00:54:13 CST"
    },
    {
      "x": 4.807812744298899,
      "y": 0.26933101449737906,
      "t": "2026-03-27 00:54:13 CST"
    },
    {
      "x": 4.896839459759527,
      "y": 0.3297843031806061,
      "t": "2026-03-27 00:54:14 CST"
    },
    {
      "x": 4.982029672192307,
      "y": 0.35041004821925237,
      "t": "2026-03-27 00:54:14 CST"
    },
    {
      "x": 5.011790179660525,
      "y": 0.33149801075738944,
      "t": "2026-03-27 00:54:16 CST"
    },
    {
      "x": 5.022659464067539,
      "y": 0.25839447222065215,
      "t": "2026-03-27 00:54:17 CST"
    },
    {
      "x": 5.001245779377348,
      "y": 0.17030488955845888,
      "t": "2026-03-27 00:54:17 CST"
    },
    {
      "x": 4.95783145302342,
      "y": 0.09078578141760435,
      "t": "2026-03-27 00:54:17 CST"
    },
    {
      "x": 4.906224112661239,
      "y": 0.006720565704259329,
      "t": "2026-03-27 00:54:18 CST"
    },
    {
      "x": 4.880937166155095,
      "y": -0.03863321213021742,
      "t": "2026-03-27 00:54:18 CST"
    },
    {
      "x": 4.858923581051848,
      "y": -0.08937343115678159,
      "t": "2026-03-27 00:54:18 CST"
    },
    {
      "x": 4.839653352791679,
      "y": -0.1357299583315797,
      "t": "2026-03-27 00:54:18 CST"
    },
    {
      "x": 4.808888086860538,
      "y": -0.22979242191209487,
      "t": "2026-03-27 00:54:19 CST"
    },
    {
      "x": 4.820756100440584,
      "y": -0.39327903871305253,
      "t": "2026-03-27 00:54:19 CST"
    },
    {
      "x": 4.8050208038439495,
      "y": -0.441473842775643,
      "t": "2026-03-27 00:54:19 CST"
    },
    {
      "x": 4.765108723927565,
      "y": -0.5330334991527486,
      "t": "2026-03-27 00:54:20 CST"
    },
    {
      "x": 4.743224044935032,
      "y": -0.5797641628279271,
      "t": "2026-03-27 00:54:20 CST"
    },
    {
      "x": 4.719656978317068,
      "y": -0.6252571113689231,
      "t": "2026-03-27 00:54:20 CST"
    },
    {
      "x": 4.696194202287907,
      "y": -0.6707704620026436,
      "t": "2026-03-27 00:54:20 CST"
    },
    {
      "x": 4.671537106298734,
      "y": -0.7158556672134746,
      "t": "2026-03-27 00:54:21 CST"
    },
    {
      "x": 4.646945560844324,
      "y": -0.7605622837625241,
      "t": "2026-03-27 00:54:21 CST"
    },
    {
      "x": 4.600430518355491,
      "y": -0.8497785153196125,
      "t": "2026-03-27 00:54:21 CST"
    },
    {
      "x": 4.578004004007904,
      "y": -0.8970090094260292,
      "t": "2026-03-27 00:54:21 CST"
    },
    {
      "x": 4.557051265045271,
      "y": -0.9432526556839422,
      "t": "2026-03-27 00:54:22 CST"
    },
    {
      "x": 4.53753485722534,
      "y": -0.9900314299224626,
      "t": "2026-03-27 00:54:22 CST"
    },
    {
      "x": 4.501735274653031,
      "y": -1.0838601872342306,
      "t": "2026-03-27 00:54:22 CST"
    },
    {
      "x": 4.482919398855349,
      "y": -1.130510115705174,
      "t": "2026-03-27 00:54:22 CST"
    },
    {
      "x": 4.424937978766803,
      "y": -1.2810014597352244,
      "t": "2026-03-27 00:54:23 CST"
    },
    {
      "x": 4.381861911868084,
      "y": -1.3730211721555314,
      "t": "2026-03-27 00:54:23 CST"
    },
    {
      "x": 4.357156523942379,
      "y": -1.416991875615591,
      "t": "2026-03-27 00:54:23 CST"
    },
    {
      "x": 4.330620913452768,
      "y": -1.4617965388925531,
      "t": "2026-03-27 00:54:24 CST"
    },
    {
      "x": 4.300621258102286,
      "y": -1.50499407317438,
      "t": "2026-03-27 00:54:24 CST"
    },
    {
      "x": 4.2684075468618285,
      "y": -1.5453651365619454,
      "t": "2026-03-27 00:54:24 CST"
    },
    {
      "x": 4.235339231007338,
      "y": -1.5851683176559221,
      "t": "2026-03-27 00:54:24 CST"
    },
    {
      "x": 4.199626530760053,
      "y": -1.6223907716515142,
      "t": "2026-03-27 00:54:24 CST"
    },
    {
      "x": 4.161561399154359,
      "y": -1.6587120099708705,
      "t": "2026-03-27 00:54:25 CST"
    },
    {
      "x": 4.1233726299202464,
      "y": -1.692260906300004,
      "t": "2026-03-27 00:54:25 CST"
    },
    {
      "x": 4.083423032994864,
      "y": -1.7241842008514132,
      "t": "2026-03-27 00:54:25 CST"
    },
    {
      "x": 4.042901683875755,
      "y": -1.7547299006621524,
      "t": "2026-03-27 00:54:25 CST"
    },
    {
      "x": 4.001777490401799,
      "y": -1.7855707697437542,
      "t": "2026-03-27 00:54:25 CST"
    },
    {
      "x": 3.9601108388637534,
      "y": -1.8155374454987572,
      "t": "2026-03-27 00:54:26 CST"
    },
    {
      "x": 3.8810654868142613,
      "y": -1.8734214892974366,
      "t": "2026-03-27 00:54:26 CST"
    },
    {
      "x": 3.8390879408697383,
      "y": -1.9043667486093727,
      "t": "2026-03-27 00:54:26 CST"
    },
    {
      "x": 3.7681672177874614,
      "y": -1.9745724386662535,
      "t": "2026-03-27 00:54:26 CST"
    },
    {
      "x": 3.7290120801482285,
      "y": -2.008457440342495,
      "t": "2026-03-27 00:54:27 CST"
    },
    {
      "x": 3.690298763505944,
      "y": -2.044270220406255,
      "t": "2026-03-27 00:54:27 CST"
    },
    {
      "x": 3.654967849633175,
      "y": -2.084831920175639,
      "t": "2026-03-27 00:54:27 CST"
    },
    {
      "x": 3.624907925630421,
      "y": -2.1275365047479795,
      "t": "2026-03-27 00:54:27 CST"
    },
    {
      "x": 3.599973812204355,
      "y": -2.1727589850864004,
      "t": "2026-03-27 00:54:27 CST"
    },
    {
      "x": 3.569412324796039,
      "y": -2.2632380486018384,
      "t": "2026-03-27 00:54:28 CST"
    },
    {
      "x": 3.530379116735747,
      "y": -2.356605464491758,
      "t": "2026-03-27 00:54:28 CST"
    },
    {
      "x": 3.515086614572388,
      "y": -2.451439882679821,
      "t": "2026-03-27 00:54:29 CST"
    },
    {
      "x": 3.50728407835058,
      "y": -2.5008608161255244,
      "t": "2026-03-27 00:54:29 CST"
    },
    {
      "x": 3.4974949248418885,
      "y": -2.5508295069004068,
      "t": "2026-03-27 00:54:29 CST"
    },
    {
      "x": 3.484019618722471,
      "y": -2.599401015825458,
      "t": "2026-03-27 00:54:29 CST"
    },
    {
      "x": 3.4651752479419806,
      "y": -2.646964963584109,
      "t": "2026-03-27 00:54:29 CST"
    },
    {
      "x": 3.4406876903887538,
      "y": -2.6931884315429544,
      "t": "2026-03-27 00:54:30 CST"
    },
    {
      "x": 3.412661212830652,
      "y": -2.735547597788441,
      "t": "2026-03-27 00:54:30 CST"
    },
    {
      "x": 3.378542666405408,
      "y": -2.7732299667737763,
      "t": "2026-03-27 00:54:30 CST"
    },
    {
      "x": 3.3382607188765823,
      "y": -2.806799907089812,
      "t": "2026-03-27 00:54:30 CST"
    },
    {
      "x": 3.296475975779382,
      "y": -2.8353546929104376,
      "t": "2026-03-27 00:54:30 CST"
    },
    {
      "x": 3.2504479128733674,
      "y": -2.8612830180092814,
      "t": "2026-03-27 00:54:31 CST"
    },
    {
      "x": 3.204488246550537,
      "y": -2.8836960477438183,
      "t": "2026-03-27 00:54:31 CST"
    },
    {
      "x": 3.1586797477235766,
      "y": -2.9038583727440135,
      "t": "2026-03-27 00:54:31 CST"
    },
    {
      "x": 3.1114215791175517,
      "y": -2.9238742913186773,
      "t": "2026-03-27 00:54:31 CST"
    },
    {
      "x": 3.0616544751151373,
      "y": -2.9403918093132844,
      "t": "2026-03-27 00:54:31 CST"
    },
    {
      "x": 3.013570692109408,
      "y": -2.954891288622281,
      "t": "2026-03-27 00:54:32 CST"
    },
    {
      "x": 2.9648187816215406,
      "y": -3.004092505568848,
      "t": "2026-03-27 00:54:32 CST"
    },
    {
      "x": 2.9158742354672746,
      "y": -3.026665331023866,
      "t": "2026-03-27 00:54:32 CST"
    },
    {
      "x": 2.867190926349771,
      "y": -3.0406369502183668,
      "t": "2026-03-27 00:54:32 CST"
    },
    {
      "x": 2.7704066639696237,
      "y": -3.0684193565439126,
      "t": "2026-03-27 00:54:33 CST"
    },
    {
      "x": 2.720407491681406,
      "y": -3.0819187811276594,
      "t": "2026-03-27 00:54:33 CST"
    },
    {
      "x": 2.670196833737906,
      "y": -3.095215207473839,
      "t": "2026-03-27 00:54:33 CST"
    },
    {
      "x": 2.6197219589310423,
      "y": -3.10940058865919,
      "t": "2026-03-27 00:54:33 CST"
    },
    {
      "x": 2.5701859826149773,
      "y": -3.123406139844671,
      "t": "2026-03-27 00:54:33 CST"
    },
    {
      "x": 2.5187484959051547,
      "y": -3.1392497498586533,
      "t": "2026-03-27 00:54:34 CST"
    },
    {
      "x": 2.4688433239463845,
      "y": -3.154443105878812,
      "t": "2026-03-27 00:54:34 CST"
    },
    {
      "x": 2.419354282509845,
      "y": -3.1717464396127757,
      "t": "2026-03-27 00:54:34 CST"
    },
    {
      "x": 2.3719258597326838,
      "y": -3.190860650612635,
      "t": "2026-03-27 00:54:34 CST"
    },
    {
      "x": 2.2895857466447023,
      "y": -3.2331702270059934,
      "t": "2026-03-27 00:54:35 CST"
    },
    {
      "x": 2.2460100940384717,
      "y": -3.266846459289675,
      "t": "2026-03-27 00:54:35 CST"
    },
    {
      "x": 2.2177411141816776,
      "y": -3.300090783640474,
      "t": "2026-03-27 00:54:36 CST"
    },
    {
      "x": 2.1728607796086576,
      "y": -3.318559823945108,
      "t": "2026-03-27 00:54:36 CST"
    },
    {
      "x": 2.1512625817690374,
      "y": -3.3326505121323486,
      "t": "2026-03-27 00:54:39 CST"
    },
    {
      "x": 2.1255001279544965,
      "y": -3.3429940358291246,
      "t": "2026-03-27 00:54:40 CST"
    },
    {
      "x": 2.0991931024837287,
      "y": -3.358830079732004,
      "t": "2026-03-27 00:54:40 CST"
    },
    {
      "x": 2.075843696152808,
      "y": -3.3792224624960125,
      "t": "2026-03-27 00:54:42 CST"
    },
    {
      "x": 2.055904969230757,
      "y": -3.3952979155129395,
      "t": "2026-03-27 00:54:43 CST"
    },
    {
      "x": 2.031246895921382,
      "y": -3.4077360690942213,
      "t": "2026-03-27 00:54:45 CST"
    },
    {
      "x": 2.0030876836659566,
      "y": -3.420404056492598,
      "t": "2026-03-27 00:54:46 CST"
    },
    {
      "x": 1.9806261802267067,
      "y": -3.4365216580246174,
      "t": "2026-03-27 00:54:47 CST"
    },
    {
      "x": 1.958714877388318,
      "y": -3.4589645285473902,
      "t": "2026-03-27 00:54:49 CST"
    },
    {
      "x": 1.9313082182502037,
      "y": -3.4816567758831294,
      "t": "2026-03-27 00:54:49 CST"
    },
    {
      "x": 1.9085528356151151,
      "y": -3.492963657630328,
      "t": "2026-03-27 00:54:50 CST"
    },
    {
      "x": 1.8849783735864856,
      "y": -3.502035551904901,
      "t": "2026-03-27 00:54:51 CST"
    },
    {
      "x": 1.9082560848967935,
      "y": -3.455326573240584,
      "t": "2026-03-27 00:55:00 CST"
    },
    {
      "x": 1.9817736071770446,
      "y": -3.4130869304891074,
      "t": "2026-03-27 00:55:00 CST"
    },
    {
      "x": 2.0714956229822548,
      "y": -3.3895489760955027,
      "t": "2026-03-27 00:55:00 CST"
    },
    {
      "x": 2.1680245371268088,
      "y": -3.3672190912142232,
      "t": "2026-03-27 00:55:01 CST"
    },
    {
      "x": 2.2173614711372904,
      "y": -3.3549758953386526,
      "t": "2026-03-27 00:55:01 CST"
    },
    {
      "x": 2.266641103061626,
      "y": -3.342883674878923,
      "t": "2026-03-27 00:55:01 CST"
    },
    {
      "x": 2.3175435439210688,
      "y": -3.3289686005005046,
      "t": "2026-03-27 00:55:01 CST"
    },
    {
      "x": 2.3665866853793975,
      "y": -3.3151779260377876,
      "t": "2026-03-27 00:55:02 CST"
    },
    {
      "x": 2.4606365295394923,
      "y": -3.2899718985090067,
      "t": "2026-03-27 00:55:02 CST"
    },
    {
      "x": 2.5114208791743096,
      "y": -3.276319722317918,
      "t": "2026-03-27 00:55:02 CST"
    },
    {
      "x": 2.5626260944379986,
      "y": -3.262635539737816,
      "t": "2026-03-27 00:55:02 CST"
    },
    {
      "x": 2.6124041183301863,
      "y": -3.2477505675880027,
      "t": "2026-03-27 00:55:03 CST"
    },
    {
      "x": 2.661899419062781,
      "y": -3.2320209647638274,
      "t": "2026-03-27 00:55:03 CST"
    },
    {
      "x": 2.711356613287868,
      "y": -3.216060424403907,
      "t": "2026-03-27 00:55:03 CST"
    },
    {
      "x": 2.7862837845321193,
      "y": -3.157591723674038,
      "t": "2026-03-27 00:55:03 CST"
    },
    {
      "x": 2.757871552013176,
      "y": -3.1706048399907947,
      "t": "2026-03-27 00:55:10 CST"
    },
    {
      "x": 2.730556706468484,
      "y": -3.180630170460678,
      "t": "2026-03-27 00:55:11 CST"
    },
    {
      "x": 2.7012615907867548,
      "y": -3.1929578526811544,
      "t": "2026-03-27 00:55:12 CST"
    },
    {
      "x": 2.6721611437207575,
      "y": -3.20547075460499,
      "t": "2026-03-27 00:55:12 CST"
    },
    {
      "x": 2.6428030897188663,
      "y": -3.218505645988936,
      "t": "2026-03-27 00:55:13 CST"
    },
    {
      "x": 2.6150704183153293,
      "y": -3.230226573156339,
      "t": "2026-03-27 00:55:13 CST"
    },
    {
      "x": 2.5882890948910138,
      "y": -3.240971240916993,
      "t": "2026-03-27 00:55:14 CST"
    },
    {
      "x": 2.564479283761511,
      "y": -3.252786881346474,
      "t": "2026-03-27 00:55:15 CST"
    },
    {
      "x": 2.539314415123257,
      "y": -3.2636017852557475,
      "t": "2026-03-27 00:55:15 CST"
    },
    {
      "x": 2.578324880780771,
      "y": -3.2491959867959666,
      "t": "2026-03-27 00:55:16 CST"
    },
    {
      "x": 2.667738682896601,
      "y": -3.2289440512774283,
      "t": "2026-03-27 00:55:17 CST"
    },
    {
      "x": 2.767228872531107,
      "y": -3.224275665217903,
      "t": "2026-03-27 00:55:17 CST"
    },
    {
      "x": 2.821288747808737,
      "y": -3.2248607685557293,
      "t": "2026-03-27 00:55:17 CST"
    },
    {
      "x": 2.871402183978179,
      "y": -3.22610877042688,
      "t": "2026-03-27 00:55:17 CST"
    },
    {
      "x": 2.9727604026022587,
      "y": -3.229629936031895,
      "t": "2026-03-27 00:55:18 CST"
    },
    {
      "x": 3.0264365938499282,
      "y": -3.232039616395572,
      "t": "2026-03-27 00:55:18 CST"
    },
    {
      "x": 3.078824773854661,
      "y": -3.231829931243787,
      "t": "2026-03-27 00:55:18 CST"
    },
    {
      "x": 3.1306630922872007,
      "y": -3.2312422859916903,
      "t": "2026-03-27 00:55:18 CST"
    },
    {
      "x": 3.1824743675245433,
      "y": -3.2283601358198126,
      "t": "2026-03-27 00:55:19 CST"
    },
    {
      "x": 3.2345782819819755,
      "y": -3.2261882064796086,
      "t": "2026-03-27 00:55:19 CST"
    },
    {
      "x": 3.333360792288229,
      "y": -3.2187930120346846,
      "t": "2026-03-27 00:55:19 CST"
    },
    {
      "x": 3.434039679228621,
      "y": -3.2105121599244946,
      "t": "2026-03-27 00:55:20 CST"
    },
    {
      "x": 3.5317817764408304,
      "y": -3.2023610604826733,
      "t": "2026-03-27 00:55:20 CST"
    },
    {
      "x": 3.586213008239205,
      "y": -3.1977517872273786,
      "t": "2026-03-27 00:55:20 CST"
    },
    {
      "x": 3.7422701211416665,
      "y": -3.194627972669796,
      "t": "2026-03-27 00:55:21 CST"
    },
    {
      "x": 3.8408698271051858,
      "y": -3.1953065962130607,
      "t": "2026-03-27 00:55:21 CST"
    },
    {
      "x": 3.8910248169231005,
      "y": -3.196438184425609,
      "t": "2026-03-27 00:55:21 CST"
    },
    {
      "x": 3.941018679164844,
      "y": -3.1973902480859127,
      "t": "2026-03-27 00:55:21 CST"
    },
    {
      "x": 4.041833839237321,
      "y": -3.196464889900033,
      "t": "2026-03-27 00:55:22 CST"
    },
    {
      "x": 4.096024226707847,
      "y": -3.195549833639793,
      "t": "2026-03-27 00:55:22 CST"
    },
    {
      "x": 4.147783424929433,
      "y": -3.193413916638756,
      "t": "2026-03-27 00:55:22 CST"
    },
    {
      "x": 4.199592799619425,
      "y": -3.188239536659255,
      "t": "2026-03-27 00:55:22 CST"
    },
    {
      "x": 4.251576627594442,
      "y": -3.1796625634721125,
      "t": "2026-03-27 00:55:23 CST"
    },
    {
      "x": 4.302218291077211,
      "y": -3.166523052323443,
      "t": "2026-03-27 00:55:23 CST"
    },
    {
      "x": 4.352342628520018,
      "y": -3.149053338522536,
      "t": "2026-03-27 00:55:23 CST"
    },
    {
      "x": 4.398714096967719,
      "y": -3.1274598483050786,
      "t": "2026-03-27 00:55:23 CST"
    },
    {
      "x": 4.482262161703791,
      "y": -3.0723547828941338,
      "t": "2026-03-27 00:55:24 CST"
    },
    {
      "x": 4.521082779469493,
      "y": -3.037857368893403,
      "t": "2026-03-27 00:55:24 CST"
    },
    {
      "x": 4.643055054119034,
      "y": -2.9496192999382362,
      "t": "2026-03-27 00:55:24 CST"
    },
    {
      "x": 4.694153771072583,
      "y": -2.863881254490617,
      "t": "2026-03-27 00:55:25 CST"
    },
    {
      "x": 4.7337747041442375,
      "y": -2.774737761774015,
      "t": "2026-03-27 00:55:25 CST"
    },
    {
      "x": 4.751379949526689,
      "y": -2.727121508733898,
      "t": "2026-03-27 00:55:25 CST"
    },
    {
      "x": 4.779757212792985,
      "y": -2.6352402385595837,
      "t": "2026-03-27 00:55:26 CST"
    },
    {
      "x": 4.802357923269114,
      "y": -2.5400169660500076,
      "t": "2026-03-27 00:55:26 CST"
    },
    {
      "x": 4.820443356516326,
      "y": -2.4446831807223575,
      "t": "2026-03-27 00:55:26 CST"
    },
    {
      "x": 4.832943128950884,
      "y": -2.3926383514598704,
      "t": "2026-03-27 00:55:27 CST"
    },
    {
      "x": 4.844486685188766,
      "y": -2.3438766078525672,
      "t": "2026-03-27 00:55:27 CST"
    },
    {
      "x": 4.868311149509847,
      "y": -2.247511026645203,
      "t": "2026-03-27 00:55:27 CST"
    },
    {
      "x": 4.880719589611744,
      "y": -2.1966542164166505,
      "t": "2026-03-27 00:55:27 CST"
    },
    {
      "x": 4.905326408105673,
      "y": -2.1016459043297044,
      "t": "2026-03-27 00:55:28 CST"
    },
    {
      "x": 4.917896065395286,
      "y": -2.051967673040448,
      "t": "2026-03-27 00:55:28 CST"
    },
    {
      "x": 4.944584725350753,
      "y": -1.9543524395384098,
      "t": "2026-03-27 00:55:28 CST"
    },
    {
      "x": 4.958290925440007,
      "y": -1.9050110836403529,
      "t": "2026-03-27 00:55:29 CST"
    },
    {
      "x": 4.989572859402192,
      "y": -1.8122724076881127,
      "t": "2026-03-27 00:55:29 CST"
    },
    {
      "x": 5.007495432246504,
      "y": -1.764413049603955,
      "t": "2026-03-27 00:55:29 CST"
    },
    {
      "x": 5.027584260595409,
      "y": -1.7180243547650513,
      "t": "2026-03-27 00:55:29 CST"
    },
    {
      "x": 5.068684711882647,
      "y": -1.6278891468384802,
      "t": "2026-03-27 00:55:30 CST"
    },
    {
      "x": 5.129922339831054,
      "y": -1.5228120363617057,
      "t": "2026-03-27 00:55:30 CST"
    },
    {
      "x": 5.15390558244962,
      "y": -1.4761342539278586,
      "t": "2026-03-27 00:55:30 CST"
    },
    {
      "x": 5.195092788480641,
      "y": -1.3881195677894858,
      "t": "2026-03-27 00:55:31 CST"
    },
    {
      "x": 5.216250319197005,
      "y": -1.3427483283046537,
      "t": "2026-03-27 00:55:31 CST"
    },
    {
      "x": 5.235884368506801,
      "y": -1.2959457537343415,
      "t": "2026-03-27 00:55:31 CST"
    },
    {
      "x": 5.272388806740529,
      "y": -1.205888707085183,
      "t": "2026-03-27 00:55:31 CST"
    },
    {
      "x": 5.311317293854926,
      "y": -1.1131732986930838,
      "t": "2026-03-27 00:55:32 CST"
    },
    {
      "x": 5.347954827980726,
      "y": -1.0261797879179848,
      "t": "2026-03-27 00:55:32 CST"
    },
    {
      "x": 5.392519265285566,
      "y": -0.9361991608621612,
      "t": "2026-03-27 00:55:33 CST"
    },
    {
      "x": 5.417519557417432,
      "y": -0.8925476325058637,
      "t": "2026-03-27 00:55:33 CST"
    },
    {
      "x": 5.445462900481008,
      "y": -0.8492252830802598,
      "t": "2026-03-27 00:55:33 CST"
    },
    {
      "x": 5.475902843144535,
      "y": -0.8060494740852873,
      "t": "2026-03-27 00:55:33 CST"
    },
    {
      "x": 5.507872490520816,
      "y": -0.7666893505934502,
      "t": "2026-03-27 00:55:33 CST"
    },
    {
      "x": 5.5841896906788,
      "y": -0.6698342405006379,
      "t": "2026-03-27 00:55:34 CST"
    },
    {
      "x": 5.620235021232003,
      "y": -0.6334592121394704,
      "t": "2026-03-27 00:55:34 CST"
    },
    {
      "x": 5.657255938412466,
      "y": -0.5979077016843841,
      "t": "2026-03-27 00:55:34 CST"
    },
    {
      "x": 5.6954618088476785,
      "y": -0.5635796612696164,
      "t": "2026-03-27 00:55:34 CST"
    },
    {
      "x": 5.735328306051939,
      "y": -0.5284274330562779,
      "t": "2026-03-27 00:55:34 CST"
    },
    {
      "x": 5.7746358019091355,
      "y": -0.4928579539320028,
      "t": "2026-03-27 00:55:35 CST"
    },
    {
      "x": 5.812930009193762,
      "y": -0.4579927167747877,
      "t": "2026-03-27 00:55:35 CST"
    },
    {
      "x": 5.850771534671591,
      "y": -0.4212111547049311,
      "t": "2026-03-27 00:55:35 CST"
    },
    {
      "x": 5.888528381621382,
      "y": -0.3845173524026625,
      "t": "2026-03-27 00:55:35 CST"
    },
    {
      "x": 5.92544480238938,
      "y": -0.34817741133027014,
      "t": "2026-03-27 00:55:35 CST"
    },
    {
      "x": 5.961308703622342,
      "y": -0.3107430213361323,
      "t": "2026-03-27 00:55:36 CST"
    },
    {
      "x": 5.995333733215479,
      "y": -0.27398535759492015,
      "t": "2026-03-27 00:55:36 CST"
    },
    {
      "x": 6.030579311506283,
      "y": -0.2362951083942928,
      "t": "2026-03-27 00:55:36 CST"
    },
    {
      "x": 6.064751946759639,
      "y": -0.19945242554820752,
      "t": "2026-03-27 00:55:36 CST"
    },
    {
      "x": 6.099050433669197,
      "y": -0.16161856709602107,
      "t": "2026-03-27 00:55:36 CST"
    },
    {
      "x": 6.134067106847087,
      "y": -0.1230995878508574,
      "t": "2026-03-27 00:55:37 CST"
    },
    {
      "x": 6.1682704038766,
      "y": -0.08389002551288205,
      "t": "2026-03-27 00:55:37 CST"
    },
    {
      "x": 6.255027801123219,
      "y": 0.009572940348593129,
      "t": "2026-03-27 00:55:37 CST"
    },
    {
      "x": 6.288571800728239,
      "y": 0.04817015732600127,
      "t": "2026-03-27 00:55:37 CST"
    },
    {
      "x": 6.354259661126188,
      "y": 0.11838347085999112,
      "t": "2026-03-27 00:55:38 CST"
    },
    {
      "x": 6.390603670150957,
      "y": 0.15734157795231923,
      "t": "2026-03-27 00:55:38 CST"
    },
    {
      "x": 6.4263891097189605,
      "y": 0.19695325972084304,
      "t": "2026-03-27 00:55:38 CST"
    },
    {
      "x": 6.493813044096764,
      "y": 0.27088696527710854,
      "t": "2026-03-27 00:55:39 CST"
    },
    {
      "x": 6.529408677054595,
      "y": 0.3102752691471759,
      "t": "2026-03-27 00:55:39 CST"
    },
    {
      "x": 6.5643721585219215,
      "y": 0.346784136580143,
      "t": "2026-03-27 00:55:39 CST"
    },
    {
      "x": 6.599543073652698,
      "y": 0.3835115581889538,
      "t": "2026-03-27 00:55:39 CST"
    },
    {
      "x": 6.635417301972032,
      "y": 0.42022097538398184,
      "t": "2026-03-27 00:55:39 CST"
    },
    {
      "x": 6.671083071967548,
      "y": 0.45553222438277086,
      "t": "2026-03-27 00:55:40 CST"
    },
    {
      "x": 6.708311307206405,
      "y": 0.49099804085670673,
      "t": "2026-03-27 00:55:40 CST"
    },
    {
      "x": 6.747658121982379,
      "y": 0.5269530936343989,
      "t": "2026-03-27 00:55:40 CST"
    },
    {
      "x": 6.7866709744832265,
      "y": 0.5603013396961367,
      "t": "2026-03-27 00:55:40 CST"
    },
    {
      "x": 6.865167680090587,
      "y": 0.6196248970169913,
      "t": "2026-03-27 00:55:41 CST"
    },
    {
      "x": 6.934403316594181,
      "y": 0.6726458922265086,
      "t": "2026-03-27 00:55:41 CST"
    },
    {
      "x": 7.02335997339481,
      "y": 0.7183654607928176,
      "t": "2026-03-27 00:55:41 CST"
    },
    {
      "x": 7.071048318227001,
      "y": 0.7399394161562868,
      "t": "2026-03-27 00:55:42 CST"
    },
    {
      "x": 7.119794564415211,
      "y": 0.7603316200840747,
      "t": "2026-03-27 00:55:42 CST"
    },
    {
      "x": 7.1678387725223605,
      "y": 0.7780830723527853,
      "t": "2026-03-27 00:55:42 CST"
    },
    {
      "x": 7.215388315586747,
      "y": 0.7947656168960211,
      "t": "2026-03-27 00:55:42 CST"
    },
    {
      "x": 7.265402196805206,
      "y": 0.8110314093560238,
      "t": "2026-03-27 00:55:42 CST"
    },
    {
      "x": 7.316333126798079,
      "y": 0.8265089023833456,
      "t": "2026-03-27 00:55:43 CST"
    },
    {
      "x": 7.367502071971134,
      "y": 0.8428418187028084,
      "t": "2026-03-27 00:55:43 CST"
    },
    {
      "x": 7.443876811378567,
      "y": 0.866390609989409,
      "t": "2026-03-27 00:55:43 CST"
    },
    {
      "x": 7.468893208959384,
      "y": 0.8727154223550082,
      "t": "2026-03-27 00:55:46 CST"
    },
    {
      "x": 7.523572755887563,
      "y": 0.8841796515255346,
      "t": "2026-03-27 00:55:46 CST"
    },
    {
      "x": 7.611306780572014,
      "y": 0.8917606394770594,
      "t": "2026-03-27 00:55:46 CST"
    },
    {
      "x": 7.71006886864527,
      "y": 0.8911613779870551,
      "t": "2026-03-27 00:55:47 CST"
    },
    {
      "x": 7.761359132763782,
      "y": 0.8884152010412982,
      "t": "2026-03-27 00:55:47 CST"
    },
    {
      "x": 7.893751199299572,
      "y": 0.8641894884876545,
      "t": "2026-03-27 00:55:47 CST"
    },
    {
      "x": 7.947243542120155,
      "y": 0.8610318083267725,
      "t": "2026-03-27 00:55:47 CST"
    },
    {
      "x": 8.003625252907048,
      "y": 0.8593393355027356,
      "t": "2026-03-27 00:55:48 CST"
    },
    {
      "x": 8.05910160514598,
      "y": 0.859676656574094,
      "t": "2026-03-27 00:55:48 CST"
    },
    {
      "x": 8.11372761905138,
      "y": 0.8639772724267728,
      "t": "2026-03-27 00:55:48 CST"
    },
    {
      "x": 8.16669182798515,
      "y": 0.8716217060220371,
      "t": "2026-03-27 00:55:48 CST"
    },
    {
      "x": 8.217488414021144,
      "y": 0.8824609713514947,
      "t": "2026-03-27 00:55:48 CST"
    },
    {
      "x": 8.26566799187655,
      "y": 0.8958923158756911,
      "t": "2026-03-27 00:55:49 CST"
    },
    {
      "x": 8.363187325190934,
      "y": 0.9274670713559584,
      "t": "2026-03-27 00:55:49 CST"
    },
    {
      "x": 8.450309460959858,
      "y": 0.9584352614753249,
      "t": "2026-03-27 00:55:49 CST"
    },
    {
      "x": 8.544247119033589,
      "y": 0.9875021356154364,
      "t": "2026-03-27 00:55:50 CST"
    },
    {
      "x": 8.641630004837406,
      "y": 1.0102220620450273,
      "t": "2026-03-27 00:55:50 CST"
    },
    {
      "x": 8.768470261972691,
      "y": 0.9986248643306442,
      "t": "2026-03-27 00:55:51 CST"
    },
    {
      "x": 8.868308936377264,
      "y": 0.9982985707662263,
      "t": "2026-03-27 00:55:51 CST"
    },
    {
      "x": 8.968085284386907,
      "y": 0.9959847414300407,
      "t": "2026-03-27 00:55:51 CST"
    },
    {
      "x": 9.020489786711408,
      "y": 0.9952168077717856,
      "t": "2026-03-27 00:55:52 CST"
    },
    {
      "x": 9.07299322170476,
      "y": 0.9960584995991908,
      "t": "2026-03-27 00:55:52 CST"
    },
    {
      "x": 9.123710404560399,
      "y": 0.9969858616570777,
      "t": "2026-03-27 00:55:52 CST"
    },
    {
      "x": 9.17472810771028,
      "y": 0.9982256276953281,
      "t": "2026-03-27 00:55:52 CST"
    },
    {
      "x": 9.273382650515817,
      "y": 1.0030209917111697,
      "t": "2026-03-27 00:55:53 CST"
    },
    {
      "x": 9.323407853401548,
      "y": 1.0070328016780252,
      "t": "2026-03-27 00:55:53 CST"
    },
    {
      "x": 9.37610075172072,
      "y": 1.0108027663017862,
      "t": "2026-03-27 00:55:53 CST"
    },
    {
      "x": 9.475327503452554,
      "y": 1.0204398882585302,
      "t": "2026-03-27 00:55:53 CST"
    },
    {
      "x": 9.525257720212107,
      "y": 1.0237904767172383,
      "t": "2026-03-27 00:55:54 CST"
    },
    {
      "x": 9.62512230731692,
      "y": 1.0284515705893236,
      "t": "2026-03-27 00:55:54 CST"
    },
    {
      "x": 9.676021221366293,
      "y": 1.029621891906499,
      "t": "2026-03-27 00:55:54 CST"
    },
    {
      "x": 9.807516691220846,
      "y": 1.0316568993883934,
      "t": "2026-03-27 00:55:54 CST"
    },
    {
      "x": 9.859085868582788,
      "y": 1.0346044124261415,
      "t": "2026-03-27 00:55:55 CST"
    },
    {
      "x": 9.913941543912697,
      "y": 1.039744309063322,
      "t": "2026-03-27 00:55:55 CST"
    },
    {
      "x": 9.969412197121414,
      "y": 1.0483333620185704,
      "t": "2026-03-27 00:55:55 CST"
    },
    {
      "x": 10.020003867888583,
      "y": 1.0607181584092022,
      "t": "2026-03-27 00:55:55 CST"
    },
    {
      "x": 10.086990963148649,
      "y": 1.0892243255490086,
      "t": "2026-03-27 00:55:56 CST"
    },
    {
      "x": 10.132194025565678,
      "y": 1.1382831850507615,
      "t": "2026-03-27 00:55:56 CST"
    },
    {
      "x": 10.15232984294253,
      "y": 1.1549158359067717,
      "t": "2026-03-27 00:55:58 CST"
    },
    {
      "x": 10.187526682921023,
      "y": 1.162696280885733,
      "t": "2026-03-27 00:55:59 CST"
    },
    {
      "x": 10.266723599289852,
      "y": 1.1693116822738436,
      "t": "2026-03-27 00:55:59 CST"
    },
    {
      "x": 10.361159600811847,
      "y": 1.158955115840285,
      "t": "2026-03-27 00:55:59 CST"
    },
    {
      "x": 10.411799461901612,
      "y": 1.1470928159616698,
      "t": "2026-03-27 00:56:00 CST"
    },
    {
      "x": 10.505516886436453,
      "y": 1.117657690646104,
      "t": "2026-03-27 00:56:00 CST"
    },
    {
      "x": 10.556794161409835,
      "y": 1.1017337609041298,
      "t": "2026-03-27 00:56:00 CST"
    },
    {
      "x": 10.608634905910128,
      "y": 1.0874601503496417,
      "t": "2026-03-27 00:56:00 CST"
    },
    {
      "x": 10.662454495486195,
      "y": 1.0761527798750758,
      "t": "2026-03-27 00:56:01 CST"
    },
    {
      "x": 10.7494451056869,
      "y": 1.0332862942869943,
      "t": "2026-03-27 00:56:01 CST"
    },
    {
      "x": 10.801984437772298,
      "y": 1.0350902065704064,
      "t": "2026-03-27 00:56:01 CST"
    },
    {
      "x": 10.890928837062816,
      "y": 1.0582717682398572,
      "t": "2026-03-27 00:56:01 CST"
    },
    {
      "x": 10.967259918599538,
      "y": 1.108511430711979,
      "t": "2026-03-27 00:56:02 CST"
    },
    {
      "x": 11.033686418927916,
      "y": 1.1741496269389422,
      "t": "2026-03-27 00:56:02 CST"
    },
    {
      "x": 11.08830782285194,
      "y": 1.2462859127265178,
      "t": "2026-03-27 00:56:03 CST"
    },
    {
      "x": 11.131512293204873,
      "y": 1.305692974369738,
      "t": "2026-03-27 00:56:03 CST"
    },
    {
      "x": 11.168996921752415,
      "y": 1.346333411452716,
      "t": "2026-03-27 00:56:03 CST"
    },
    {
      "x": 11.197109819989102,
      "y": 1.3712599824802552,
      "t": "2026-03-27 00:56:04 CST"
    },
    {
      "x": 11.219127904592645,
      "y": 1.3876394494213102,
      "t": "2026-03-27 00:56:05 CST"
    },
    {
      "x": 11.24685047072976,
      "y": 1.4054656321584347,
      "t": "2026-03-27 00:56:06 CST"
    },
    {
      "x": 11.278597875096343,
      "y": 1.4187552787822204,
      "t": "2026-03-27 00:56:06 CST"
    },
    {
      "x": 11.312432989773809,
      "y": 1.4251476978624116,
      "t": "2026-03-27 00:56:08 CST"
    },
    {
      "x": 11.33747610069389,
      "y": 1.4353730526234472,
      "t": "2026-03-27 00:56:08 CST"
    },
    {
      "x": 11.26583753299238,
      "y": 1.4432805334206193,
      "t": "2026-03-27 00:56:16 CST"
    },
    {
      "x": 11.292365368755808,
      "y": 1.449548530260921,
      "t": "2026-03-27 00:56:19 CST"
    },
    {
      "x": 11.369869639860955,
      "y": 1.435655509087483,
      "t": "2026-03-27 00:56:19 CST"
    },
    {
      "x": 11.435852768661684,
      "y": 1.3884476362245,
      "t": "2026-03-27 00:56:20 CST"
    },
    {
      "x": 11.493803160745266,
      "y": 1.3207054225789077,
      "t": "2026-03-27 00:56:20 CST"
    },
    {
      "x": 11.556182468763037,
      "y": 1.2413846336754184,
      "t": "2026-03-27 00:56:20 CST"
    },
    {
      "x": 11.591468068761502,
      "y": 1.2024313194460032,
      "t": "2026-03-27 00:56:21 CST"
    },
    {
      "x": 11.629990010915972,
      "y": 1.165310950832168,
      "t": "2026-03-27 00:56:21 CST"
    },
    {
      "x": 11.672041673483463,
      "y": 1.1357999130034055,
      "t": "2026-03-27 00:56:21 CST"
    },
    {
      "x": 11.901495504699524,
      "y": 1.0997171807593615,
      "t": "2026-03-27 00:56:21 CST"
    },
    {
      "x": 11.992390228121433,
      "y": 1.0866536510660538,
      "t": "2026-03-27 00:56:22 CST"
    },
    {
      "x": 12.085130981299494,
      "y": 1.08521649351717,
      "t": "2026-03-27 00:56:22 CST"
    },
    {
      "x": 12.18431097328869,
      "y": 1.086655474928742,
      "t": "2026-03-27 00:56:23 CST"
    },
    {
      "x": 12.23507786517684,
      "y": 1.0887722461758202,
      "t": "2026-03-27 00:56:23 CST"
    },
    {
      "x": 12.287137881473045,
      "y": 1.0910226360775486,
      "t": "2026-03-27 00:56:23 CST"
    },
    {
      "x": 12.340581577643553,
      "y": 1.094786477423918,
      "t": "2026-03-27 00:56:23 CST"
    },
    {
      "x": 12.434923129010086,
      "y": 1.0825659139052437,
      "t": "2026-03-27 00:56:23 CST"
    },
    {
      "x": 12.487266646666235,
      "y": 1.0804774848804974,
      "t": "2026-03-27 00:56:24 CST"
    },
    {
      "x": 12.539274224260478,
      "y": 1.077886018690842,
      "t": "2026-03-27 00:56:24 CST"
    },
    {
      "x": 12.590822670812528,
      "y": 1.0769836480647215,
      "t": "2026-03-27 00:56:24 CST"
    },
    {
      "x": 12.64225179136042,
      "y": 1.0767263448973665,
      "t": "2026-03-27 00:56:24 CST"
    },
    {
      "x": 12.742310679310387,
      "y": 1.079336348556401,
      "t": "2026-03-27 00:56:25 CST"
    },
    {
      "x": 12.840375813980614,
      "y": 1.0851307870855786,
      "t": "2026-03-27 00:56:25 CST"
    },
    {
      "x": 12.939194212865392,
      "y": 1.091514530330558,
      "t": "2026-03-27 00:56:25 CST"
    },
    {
      "x": 13.038522599372358,
      "y": 1.0975252552436463,
      "t": "2026-03-27 00:56:26 CST"
    },
    {
      "x": 13.08929788265458,
      "y": 1.0989406417957195,
      "t": "2026-03-27 00:56:26 CST"
    },
    {
      "x": 13.18624141333396,
      "y": 1.0990403152464734,
      "t": "2026-03-27 00:56:26 CST"
    },
    {
      "x": 13.237145736803225,
      "y": 1.0969674729447252,
      "t": "2026-03-27 00:56:27 CST"
    },
    {
      "x": 13.365859647319152,
      "y": 1.0716522822303527,
      "t": "2026-03-27 00:56:27 CST"
    },
    {
      "x": 13.463571989536822,
      "y": 1.0674342859214863,
      "t": "2026-03-27 00:56:27 CST"
    },
    {
      "x": 13.51514281343682,
      "y": 1.0649592900963327,
      "t": "2026-03-27 00:56:28 CST"
    },
    {
      "x": 13.614041676813068,
      "y": 1.059553901902342,
      "t": "2026-03-27 00:56:28 CST"
    },
    {
      "x": 13.664438283697566,
      "y": 1.0567996436688727,
      "t": "2026-03-27 00:56:28 CST"
    },
    {
      "x": 13.715056603656382,
      "y": 1.0534106201930813,
      "t": "2026-03-27 00:56:28 CST"
    },
    {
      "x": 13.76522516001596,
      "y": 1.0506414408810485,
      "t": "2026-03-27 00:56:29 CST"
    },
    {
      "x": 13.865433916647767,
      "y": 1.0448403515962235,
      "t": "2026-03-27 00:56:29 CST"
    },
    {
      "x": 13.96621211102067,
      "y": 1.0396113461465575,
      "t": "2026-03-27 00:56:29 CST"
    },
    {
      "x": 14.017338533453021,
      "y": 1.0376249926744683,
      "t": "2026-03-27 00:56:30 CST"
    },
    {
      "x": 14.07002755740655,
      "y": 1.0352138589575541,
      "t": "2026-03-27 00:56:30 CST"
    },
    {
      "x": 14.122954742758592,
      "y": 1.034448485075495,
      "t": "2026-03-27 00:56:30 CST"
    },
    {
      "x": 14.174657260271184,
      "y": 1.032994929686328,
      "t": "2026-03-27 00:56:30 CST"
    },
    {
      "x": 14.227325841110094,
      "y": 1.0340606607941396,
      "t": "2026-03-27 00:56:30 CST"
    },
    {
      "x": 14.31196309033431,
      "y": 0.9963246781949677,
      "t": "2026-03-27 00:56:31 CST"
    },
    {
      "x": 14.36695422902714,
      "y": 1.0034441753545806,
      "t": "2026-03-27 00:56:31 CST"
    },
    {
      "x": 14.415986359256255,
      "y": 1.0168628942495075,
      "t": "2026-03-27 00:56:31 CST"
    },
    {
      "x": 14.480355307497616,
      "y": 1.0533278962009396,
      "t": "2026-03-27 00:56:31 CST"
    },
    {
      "x": 14.522189711958509,
      "y": 1.0986498627943777,
      "t": "2026-03-27 00:56:32 CST"
    },
    {
      "x": 14.572883405116649,
      "y": 1.1651036602541343,
      "t": "2026-03-27 00:56:32 CST"
    },
    {
      "x": 14.634878593455792,
      "y": 1.2445130819411578,
      "t": "2026-03-27 00:56:33 CST"
    },
    {
      "x": 14.667606045417928,
      "y": 1.2843845096608613,
      "t": "2026-03-27 00:56:33 CST"
    },
    {
      "x": 14.697938570303878,
      "y": 1.3716571034933638,
      "t": "2026-03-27 00:56:33 CST"
    },
    {
      "x": 14.734773060120405,
      "y": 1.4097168703102434,
      "t": "2026-03-27 00:56:33 CST"
    },
    {
      "x": 14.770712986447545,
      "y": 1.4516695662758994,
      "t": "2026-03-27 00:56:34 CST"
    },
    {
      "x": 14.804872455773975,
      "y": 1.4957898397254747,
      "t": "2026-03-27 00:56:34 CST"
    },
    {
      "x": 14.838048545614816,
      "y": 1.5659054826977816,
      "t": "2026-03-27 00:56:34 CST"
    },
    {
      "x": 14.844756215444905,
      "y": 1.6208062766511344,
      "t": "2026-03-27 00:56:35 CST"
    },
    {
      "x": 14.843699788778084,
      "y": 1.660402887730055,
      "t": "2026-03-27 00:56:35 CST"
    },
    {
      "x": 14.865067147345329,
      "y": 1.6404357996791281,
      "t": "2026-03-27 00:56:47 CST"
    },
    {
      "x": 14.874860116482754,
      "y": 1.6082254269705953,
      "t": "2026-03-27 00:56:47 CST"
    },
    {
      "x": 14.883831087006806,
      "y": 1.577034700809134,
      "t": "2026-03-27 00:56:48 CST"
    },
    {
      "x": 14.892623774099468,
      "y": 1.545845053519154,
      "t": "2026-03-27 00:56:49 CST"
    },
    {
      "x": 14.901203741098913,
      "y": 1.5173009509075481,
      "t": "2026-03-27 00:56:49 CST"
    },
    {
      "x": 14.90954858056071,
      "y": 1.487588565874796,
      "t": "2026-03-27 00:56:50 CST"
    },
    {
      "x": 14.91718404167879,
      "y": 1.4592502722117682,
      "t": "2026-03-27 00:56:50 CST"
    },
    {
      "x": 14.925507042634026,
      "y": 1.4317957849231393,
      "t": "2026-03-27 00:56:51 CST"
    },
    {
      "x": 14.935610944366523,
      "y": 1.399272183254768,
      "t": "2026-03-27 00:56:52 CST"
    },
    {
      "x": 14.922339084948106,
      "y": 1.4295450776502436,
      "t": "2026-03-27 00:57:04 CST"
    },
    {
      "x": 14.932660821117983,
      "y": 1.498365824846833,
      "t": "2026-03-27 00:57:04 CST"
    },
    {
      "x": 14.98355186472924,
      "y": 1.5745743561406527,
      "t": "2026-03-27 00:57:04 CST"
    },
    {
      "x": 15.02274510160035,
      "y": 1.6066656061626443,
      "t": "2026-03-27 00:57:05 CST"
    },
    {
      "x": 15.107632292270914,
      "y": 1.6495259480860065,
      "t": "2026-03-27 00:57:05 CST"
    },
    {
      "x": 15.199524315013864,
      "y": 1.6795479273713927,
      "t": "2026-03-27 00:57:05 CST"
    },
    {
      "x": 15.269095775500258,
      "y": 1.7077159348051263,
      "t": "2026-03-27 00:57:06 CST"
    },
    {
      "x": 15.331464228005789,
      "y": 1.7503015326111908,
      "t": "2026-03-27 00:57:06 CST"
    },
    {
      "x": 15.411741767957057,
      "y": 1.8161870460100995,
      "t": "2026-03-27 00:57:06 CST"
    },
    {
      "x": 15.435959703912925,
      "y": 1.857756809046109,
      "t": "2026-03-27 00:57:07 CST"
    },
    {
      "x": 15.443555912234709,
      "y": 1.8819668017374165,
      "t": "2026-03-27 00:57:08 CST"
    },
    {
      "x": 15.435690498611512,
      "y": 1.8508716029897088,
      "t": "2026-03-27 00:57:19 CST"
    },
    {
      "x": 15.427447275692195,
      "y": 1.8186305768968387,
      "t": "2026-03-27 00:57:20 CST"
    },
    {
      "x": 15.418265682142287,
      "y": 1.785226848281959,
      "t": "2026-03-27 00:57:20 CST"
    },
    {
      "x": 15.40865020785082,
      "y": 1.7558439604145462,
      "t": "2026-03-27 00:57:21 CST"
    },
    {
      "x": 15.40054401103683,
      "y": 1.7276991142602303,
      "t": "2026-03-27 00:57:21 CST"
    },
    {
      "x": 15.39357101014713,
      "y": 1.6972657763979895,
      "t": "2026-03-27 00:57:22 CST"
    },
    {
      "x": 15.38585076003671,
      "y": 1.6684567751691917,
      "t": "2026-03-27 00:57:23 CST"
    },
    {
      "x": 15.377661664743801,
      "y": 1.6414524925489913,
      "t": "2026-03-27 00:57:23 CST"
    },
    {
      "x": 15.369826795738676,
      "y": 1.6130780998601877,
      "t": "2026-03-27 00:57:24 CST"
    },
    {
      "x": 15.36324202263014,
      "y": 1.5883436966704647,
      "t": "2026-03-27 00:57:24 CST"
    },
    {
      "x": 15.382928986441648,
      "y": 1.6559235816419804,
      "t": "2026-03-27 00:57:25 CST"
    },
    {
      "x": 15.40899919790321,
      "y": 1.7343663111976784,
      "t": "2026-03-27 00:57:25 CST"
    },
    {
      "x": 15.431616814328205,
      "y": 1.7956523320778865,
      "t": "2026-03-27 00:57:26 CST"
    },
    {
      "x": 15.448153738618533,
      "y": 1.837085879867426,
      "t": "2026-03-27 00:57:26 CST"
    },
    {
      "x": 15.457537387959494,
      "y": 1.8617930578295905,
      "t": "2026-03-27 00:57:31 CST"
    },
    {
      "x": 15.456920120959584,
      "y": 1.8870227697785766,
      "t": "2026-03-27 00:57:33 CST"
    },
    {
      "x": 15.45774567223328,
      "y": 1.9134444496378968,
      "t": "2026-03-27 00:58:11 CST"
    },
    {
      "x": 15.514434775328757,
      "y": 1.9458622714859635,
      "t": "2026-03-27 00:58:11 CST"
    },
    {
      "x": 15.599804207099082,
      "y": 1.954417809225797,
      "t": "2026-03-27 00:58:12 CST"
    },
    {
      "x": 15.625321874397274,
      "y": 1.949315348117798,
      "t": "2026-03-27 00:58:12 CST"
    },
    {
      "x": 15.600488990866953,
      "y": 1.955583198908538,
      "t": "2026-03-27 00:58:13 CST"
    },
    {
      "x": 15.591731276234714,
      "y": 1.922997996571405,
      "t": "2026-03-27 00:58:24 CST"
    },
    {
      "x": 15.589306531164723,
      "y": 1.8894886612012,
      "t": "2026-03-27 00:58:24 CST"
    },
    {
      "x": 15.588588481540468,
      "y": 1.8600844105899954,
      "t": "2026-03-27 00:58:25 CST"
    },
    {
      "x": 15.587934784929693,
      "y": 1.8316391706185244,
      "t": "2026-03-27 00:58:25 CST"
    },
    {
      "x": 15.586752398377058,
      "y": 1.8006052313794492,
      "t": "2026-03-27 00:58:26 CST"
    },
    {
      "x": 15.586824024586612,
      "y": 1.773415886198338,
      "t": "2026-03-27 00:58:27 CST"
    },
    {
      "x": 15.585164717364233,
      "y": 1.7409978513963245,
      "t": "2026-03-27 00:58:27 CST"
    },
    {
      "x": 15.582508424355542,
      "y": 1.7089542907350899,
      "t": "2026-03-27 00:58:28 CST"
    },
    {
      "x": 15.581154752452278,
      "y": 1.678496683316575,
      "t": "2026-03-27 00:58:28 CST"
    },
    {
      "x": 15.580203601373391,
      "y": 1.6506743385478098,
      "t": "2026-03-27 00:58:29 CST"
    },
    {
      "x": 15.617917277810983,
      "y": 1.649722761044001,
      "t": "2026-03-27 00:58:40 CST"
    },
    {
      "x": 15.652774037319961,
      "y": 1.6528186524714106,
      "t": "2026-03-27 00:58:40 CST"
    },
    {
      "x": 15.682328210993369,
      "y": 1.6553185262684302,
      "t": "2026-03-27 00:58:41 CST"
    },
    {
      "x": 15.709009144028922,
      "y": 1.6579403307007474,
      "t": "2026-03-27 00:58:41 CST"
    },
    {
      "x": 15.737619729299684,
      "y": 1.6605049098790403,
      "t": "2026-03-27 00:58:42 CST"
    },
    {
      "x": 15.769642934044501,
      "y": 1.6618693723696338,
      "t": "2026-03-27 00:58:43 CST"
    },
    {
      "x": 15.800241330546426,
      "y": 1.6652737089704184,
      "t": "2026-03-27 00:58:43 CST"
    },
    {
      "x": 15.721670420957658,
      "y": 1.7305133991677284,
      "t": "2026-03-27 00:58:43 CST"
    },
    {
      "x": 15.752446746180874,
      "y": 1.7337701700205481,
      "t": "2026-03-27 00:58:44 CST"
    },
    {
      "x": 15.780739242104202,
      "y": 1.7371042978438194,
      "t": "2026-03-27 00:58:45 CST"
    },
    {
      "x": 15.79390337786622,
      "y": 1.7588610300261265,
      "t": "2026-03-27 00:58:55 CST"
    },
    {
      "x": 15.784414223093314,
      "y": 1.7940758225447615,
      "t": "2026-03-27 00:58:56 CST"
    },
    {
      "x": 15.77520131792266,
      "y": 1.8238992106519718,
      "t": "2026-03-27 00:58:56 CST"
    },
    {
      "x": 15.765356596711195,
      "y": 1.8512039543368757,
      "t": "2026-03-27 00:58:57 CST"
    },
    {
      "x": 15.755683459646592,
      "y": 1.877766000634372,
      "t": "2026-03-27 00:58:58 CST"
    },
    {
      "x": 15.747765377630907,
      "y": 1.9051156268582132,
      "t": "2026-03-27 00:58:58 CST"
    },
    {
      "x": 15.738717133126702,
      "y": 1.9336170368643648,
      "t": "2026-03-27 00:58:59 CST"
    },
    {
      "x": 15.728389076063927,
      "y": 1.9646565111863024,
      "t": "2026-03-27 00:58:59 CST"
    },
    {
      "x": 15.719614891402772,
      "y": 1.9930567875255774,
      "t": "2026-03-27 00:59:00 CST"
    },
    {
      "x": 15.710703367803974,
      "y": 2.0201734306439887,
      "t": "2026-03-27 00:59:01 CST"
    }
  ]
}